pyload/__init__.py
pyload/__main__.py
pyload/core/__init__.py
pyload/core/log_factory.py
pyload/core/scheduler.py
pyload/core/api/__init__.py
pyload/core/config/__init__.py
pyload/core/config/default.cfg
pyload/core/config/parser.py
pyload/core/database/__init__.py
pyload/core/database/file_database.py
pyload/core/database/storage_database.py
pyload/core/database/user_database.py
pyload/core/datatypes/__init__.py
pyload/core/datatypes/data.py
pyload/core/datatypes/enums.py
pyload/core/datatypes/exceptions.py
pyload/core/datatypes/pyfile.py
pyload/core/datatypes/pypackage.py
pyload/core/managers/__init__.py
pyload/core/managers/account_manager.py
pyload/core/managers/addon_manager.py
pyload/core/managers/captcha_manager.py
pyload/core/managers/event_manager.py
pyload/core/managers/file_manager.py
pyload/core/managers/plugin_manager.py
pyload/core/managers/thread_manager.py
pyload/core/network/__init__.py
pyload/core/network/browser.py
pyload/core/network/bucket.py
pyload/core/network/cookie_jar.py
pyload/core/network/exceptions.py
pyload/core/network/request_factory.py
pyload/core/network/http/__init__.py
pyload/core/network/http/exceptions.py
pyload/core/network/http/http_chunk.py
pyload/core/network/http/http_download.py
pyload/core/network/http/http_request.py
pyload/core/network/xdcc/__init__.py
pyload/core/network/xdcc/request.py
pyload/core/threads/__init__.py
pyload/core/threads/addon_thread.py
pyload/core/threads/clicknload_thread.py
pyload/core/threads/database_thread.py
pyload/core/threads/decrypter_thread.py
pyload/core/threads/download_thread.py
pyload/core/threads/info_thread.py
pyload/core/threads/plugin_thread.py
pyload/core/utils/__init__.py
pyload/core/utils/check.py
pyload/core/utils/convert.py
pyload/core/utils/debug.py
pyload/core/utils/format.py
pyload/core/utils/fs.py
pyload/core/utils/misc.py
pyload/core/utils/parse.py
pyload/core/utils/purge.py
pyload/core/utils/seconds.py
pyload/core/utils/system.py
pyload/core/utils/old/__init__.py
pyload_ng-0.5.0a9.dev806.dist-info/LICENSE.md
pyload_ng-0.5.0a9.dev806.dist-info/METADATA
pyload_ng-0.5.0a9.dev806.dist-info/WHEEL
pyload_ng-0.5.0a9.dev806.dist-info/entry_points.txt
pyload_ng-0.5.0a9.dev806.dist-info/top_level.txt
pyload_ng-0.5.0a9.dev806.dist-info/RECORD
