Metadata-Version: 2.1
Name: pyload-ng
Version: 0.5.0a9.dev806
Summary: The free and open-source Download Manager written in pure Python
Home-page: https://pyload.net
Author: pyLoad team
Author-email: support@pyload.net
Maintainer: Walter Purcaro
Maintainer-email: vuolter@gmail.com
License: agpl3
Download-URL: https://github.com/pyload/pyload/releases
Project-URL: Source Code (mirror), https://gitlab.com/pyload/pyload
Project-URL: Source Code, https://github.com/pyload/pyload
Project-URL: Bug Tracker, https://github.com/pyload/pyload/issues
Project-URL: Documentation, https://github.com/pyload/pyload/wiki
Keywords: pyload,download-manager,one-click-hoster,download
Platform: any
Classifier: Development Status :: 3 - Alpha
Classifier: Environment :: Console
Classifier: Environment :: Plugins
Classifier: Environment :: Web Environment
Classifier: Intended Audience :: End Users/Desktop
Classifier: License :: OSI Approved :: GNU Affero General Public License v3
Classifier: Natural Language :: English
Classifier: Operating System :: MacOS :: MacOS X
Classifier: Operating System :: Microsoft :: Windows
Classifier: Operating System :: POSIX
Classifier: Programming Language :: Python
Classifier: Programming Language :: Python :: 3 :: Only
Classifier: Programming Language :: Python :: 3.6
Classifier: Programming Language :: Python :: 3.7
Classifier: Programming Language :: Python :: 3.8
Classifier: Programming Language :: Python :: 3.9
Classifier: Programming Language :: Python :: Implementation :: CPython
Classifier: Programming Language :: Python :: Implementation :: PyPy
Classifier: Topic :: Communications
Classifier: Topic :: Communications :: File Sharing
Classifier: Topic :: Internet
Classifier: Topic :: Internet :: File Transfer Protocol (FTP)
Classifier: Topic :: Internet :: WWW/HTTP
Requires-Python: >=3.6
Requires-Dist: Cheroot (~=8.4)
Requires-Dist: Flask (~=1.1)
Requires-Dist: Flask-Babel (~=1.0)
Requires-Dist: Flask-Caching (~=1.9)
Requires-Dist: Flask-Themes2 (~=0.1)
Requires-Dist: bitmath (~=1.3)
Requires-Dist: cryptography (~=3.0)
Requires-Dist: filetype (~=1.0)
Requires-Dist: Js2Py (~=0.7)
Requires-Dist: pycurl (~=7.43)
Requires-Dist: semver (~=2.10)
Requires-Dist: setuptools (>=38.3)
Provides-Extra: all
Requires-Dist: beautifulsoup4 ; extra == 'all'
Requires-Dist: colorlog ; extra == 'all'
Requires-Dist: Pillow ; extra == 'all'
Requires-Dist: pycryptodomex ; extra == 'all'
Requires-Dist: pyOpenSSL ; extra == 'all'
Requires-Dist: pyxmpp2 ; extra == 'all'
Requires-Dist: Send2Trash ; extra == 'all'
Requires-Dist: Babel ; extra == 'all'
Requires-Dist: Jinja2 ; extra == 'all'
Provides-Extra: build
Requires-Dist: Babel ; extra == 'build'
Requires-Dist: Jinja2 ; extra == 'build'
Provides-Extra: plugins
Requires-Dist: beautifulsoup4 ; extra == 'plugins'
Requires-Dist: colorlog ; extra == 'plugins'
Requires-Dist: Pillow ; extra == 'plugins'
Requires-Dist: pycryptodomex ; extra == 'plugins'
Requires-Dist: pyOpenSSL ; extra == 'plugins'
Requires-Dist: pyxmpp2 ; extra == 'plugins'
Requires-Dist: Send2Trash ; extra == 'plugins'
